<annotation>
	<folder>New Folder With Items</folder>
	<filename>1568622391040532_143.jpg</filename>
	<path>/Users/venkatesh/Desktop/cs/New Folder With Items/1568622391040532_143.jpg</path>
	<source>
		<database>Unknown</database>
	</source>
	<size>
		<width>2592</width>
		<height>1944</height>
		<depth>3</depth>
	</size>
	<segmented>0</segmented>
	<object>
		<name>shelf</name>
		<pose>Unspecified</pose>
		<truncated>0</truncated>
		<difficult>0</difficult>
		<bndbox>
			<xmin>511</xmin>
			<ymin>394</ymin>
			<xmax>2089</xmax>
			<ymax>733</ymax>
		</bndbox>
	</object>
	<object>
		<name>shelf</name>
		<pose>Unspecified</pose>
		<truncated>0</truncated>
		<difficult>0</difficult>
		<bndbox>
			<xmin>532</xmin>
			<ymin>755</ymin>
			<xmax>2107</xmax>
			<ymax>1252</ymax>
		</bndbox>
	</object>
	<object>
		<name>shelf</name>
		<pose>Unspecified</pose>
		<truncated>0</truncated>
		<difficult>0</difficult>
		<bndbox>
			<xmin>498</xmin>
			<ymin>1170</ymin>
			<xmax>2080</xmax>
			<ymax>1752</ymax>
		</bndbox>
	</object>
</annotation>
