<annotation>
	<folder>shelfimg</folder>
	<filename>i114_156862441125191_485.jpg</filename>
	<path>/home/hashstudioz/workspace/projects/cooler/labelImg-master/shelfimg/i114_156862441125191_485.jpg</path>
	<source>
		<database>Unknown</database>
	</source>
	<size>
		<width>600</width>
		<height>300</height>
		<depth>3</depth>
	</size>
	<segmented>0</segmented>
	<object>
		<name>icecream</name>
		<pose>Unspecified</pose>
		<truncated>0</truncated>
		<difficult>0</difficult>
		<bndbox>
			<xmin>58</xmin>
			<ymin>83</ymin>
			<xmax>178</xmax>
			<ymax>207</ymax>
		</bndbox>
	</object>
	<object>
		<name>icecream</name>
		<pose>Unspecified</pose>
		<truncated>0</truncated>
		<difficult>0</difficult>
		<bndbox>
			<xmin>176</xmin>
			<ymin>87</ymin>
			<xmax>308</xmax>
			<ymax>216</ymax>
		</bndbox>
	</object>
	<object>
		<name>icecream</name>
		<pose>Unspecified</pose>
		<truncated>0</truncated>
		<difficult>0</difficult>
		<bndbox>
			<xmin>307</xmin>
			<ymin>85</ymin>
			<xmax>429</xmax>
			<ymax>220</ymax>
		</bndbox>
	</object>
	<object>
		<name>icecream</name>
		<pose>Unspecified</pose>
		<truncated>0</truncated>
		<difficult>0</difficult>
		<bndbox>
			<xmin>427</xmin>
			<ymin>90</ymin>
			<xmax>553</xmax>
			<ymax>214</ymax>
		</bndbox>
	</object>
</annotation>
