<annotation>
	<folder>shelfimg</folder>
	<filename>i103_156862291551642_263.jpg</filename>
	<path>/home/hashstudioz/workspace/projects/cooler/labelImg-master/shelfimg/i103_156862291551642_263.jpg</path>
	<source>
		<database>Unknown</database>
	</source>
	<size>
		<width>600</width>
		<height>300</height>
		<depth>3</depth>
	</size>
	<segmented>0</segmented>
	<object>
		<name>icecream</name>
		<pose>Unspecified</pose>
		<truncated>0</truncated>
		<difficult>0</difficult>
		<bndbox>
			<xmin>49</xmin>
			<ymin>73</ymin>
			<xmax>167</xmax>
			<ymax>201</ymax>
		</bndbox>
	</object>
	<object>
		<name>icecream</name>
		<pose>Unspecified</pose>
		<truncated>0</truncated>
		<difficult>0</difficult>
		<bndbox>
			<xmin>165</xmin>
			<ymin>73</ymin>
			<xmax>295</xmax>
			<ymax>211</ymax>
		</bndbox>
	</object>
	<object>
		<name>icecream</name>
		<pose>Unspecified</pose>
		<truncated>0</truncated>
		<difficult>0</difficult>
		<bndbox>
			<xmin>293</xmin>
			<ymin>81</ymin>
			<xmax>430</xmax>
			<ymax>212</ymax>
		</bndbox>
	</object>
	<object>
		<name>icecream</name>
		<pose>Unspecified</pose>
		<truncated>0</truncated>
		<difficult>0</difficult>
		<bndbox>
			<xmin>427</xmin>
			<ymin>83</ymin>
			<xmax>565</xmax>
			<ymax>211</ymax>
		</bndbox>
	</object>
</annotation>
