<annotation>
	<folder>img0to400</folder>
	<filename>i115_1568622737485491_222.jpg</filename>
	<path>/home/hashstudioz/Desktop/img0to400/i115_1568622737485491_222.jpg</path>
	<source>
		<database>Unknown</database>
	</source>
	<size>
		<width>600</width>
		<height>300</height>
		<depth>3</depth>
	</size>
	<segmented>0</segmented>
	<object>
		<name>icecream</name>
		<pose>Unspecified</pose>
		<truncated>0</truncated>
		<difficult>0</difficult>
		<bndbox>
			<xmin>34</xmin>
			<ymin>101</ymin>
			<xmax>142</xmax>
			<ymax>169</ymax>
		</bndbox>
	</object>
	<object>
		<name>icecream</name>
		<pose>Unspecified</pose>
		<truncated>0</truncated>
		<difficult>0</difficult>
		<bndbox>
			<xmin>139</xmin>
			<ymin>105</ymin>
			<xmax>249</xmax>
			<ymax>173</ymax>
		</bndbox>
	</object>
	<object>
		<name>icecream</name>
		<pose>Unspecified</pose>
		<truncated>0</truncated>
		<difficult>0</difficult>
		<bndbox>
			<xmin>243</xmin>
			<ymin>118</ymin>
			<xmax>392</xmax>
			<ymax>185</ymax>
		</bndbox>
	</object>
	<object>
		<name>icecream</name>
		<pose>Unspecified</pose>
		<truncated>0</truncated>
		<difficult>0</difficult>
		<bndbox>
			<xmin>392</xmin>
			<ymin>112</ymin>
			<xmax>550</xmax>
			<ymax>196</ymax>
		</bndbox>
	</object>
</annotation>
