<annotation>
	<folder>img0to400</folder>
	<filename>i176_1568623785302548_437.jpg</filename>
	<path>/home/hashstudioz/Desktop/img0to400/i176_1568623785302548_437.jpg</path>
	<source>
		<database>Unknown</database>
	</source>
	<size>
		<width>600</width>
		<height>300</height>
		<depth>3</depth>
	</size>
	<segmented>0</segmented>
	<object>
		<name>icecream</name>
		<pose>Unspecified</pose>
		<truncated>0</truncated>
		<difficult>0</difficult>
		<bndbox>
			<xmin>49</xmin>
			<ymin>108</ymin>
			<xmax>183</xmax>
			<ymax>233</ymax>
		</bndbox>
	</object>
	<object>
		<name>icecream</name>
		<pose>Unspecified</pose>
		<truncated>0</truncated>
		<difficult>0</difficult>
		<bndbox>
			<xmin>180</xmin>
			<ymin>109</ymin>
			<xmax>311</xmax>
			<ymax>228</ymax>
		</bndbox>
	</object>
	<object>
		<name>icecream</name>
		<pose>Unspecified</pose>
		<truncated>0</truncated>
		<difficult>0</difficult>
		<bndbox>
			<xmin>431</xmin>
			<ymin>110</ymin>
			<xmax>565</xmax>
			<ymax>238</ymax>
		</bndbox>
	</object>
</annotation>
